[
    {
        "api": "ls_start_transaction",
        "args": {
            "transaction_name": "trans_1"
        }
    },

    // {
    //     "api": "http_connect",
    //     "args": {
    //         "server ip": "1.2.3.4",
    //         "server port": "80",
    //         "as connid": "my_server"
    //     }
    // },

    // {
    //     "api": "http_reg_save",
    //     "args": {
    //         "part": "reqline|head|body",
    //         "left bound": "this is ",
    //         "right bound": "world",
    //         "occurence": "once|all"
    //     }
    // },

    // {
    //     "api": "http_request",
    //     "args": {
    //         "connid": "my_server",
    //         "reqline": "POST /req1 HTTP/1.1",
    //         "headers": {
    //             "Host": "1.2.3.4"
    //             // Content-Length会自动添加
    //         },
    //         "body": "this is my request"
    //     }
    // },

    // {
    //     "api": "http_disconnect",
    //     "args": {
    //         "connid": "my_server"
    //     }
    // },

    {
        "api": "ls_think_time",
        "args": {
            "time": 3000
        }
    },

    {
        "api": "ls_end_transaction",
        "args": {
            "transaction_name": "trans_1",
            "status": "pass"
        }
    },

    {
        "api": "ls_output_message",
        "args": {
            "message": "hello world"
        }
    }
]
